[{"domain":"google.ad","tld":".ad","country_name":"Andorra","language_a_code":"ca","language_a_name":"Catalan","web":1,"images":0,"youtube":0,"news":0,"books":0,"products":0,"recipes":0,"functional":1},
{"domain":"google.iq","tld":".iq","country_name":"Iraq","language_a_code":"ckb","language_a_name":"Kurdish","web":1,"images":0,"youtube":0,"news":0,"books":0,"products":0,"recipes":0,"functional":1},
{"domain":"google.cz","tld":".cz","country_name":"Czech Republic","language_a_code":"cs","language_a_name":"Czech","web":1,"images":1,"youtube":0,"news":0,"books":0,"products":0,"recipes":0,"functional":0},
{"domain":"google.dk","tld":".dk","country_name":"Denmark","language_a_code":"da","language_a_name":"Danish","web":1,"images":1,"youtube":0,"news":0,"books":0,"products":0,"recipes":0,"functional":1},
{"domain":"google.de","tld":".de","country_name":"Germany","language_a_code":"de","language_a_name":"German","web":1,"images":1,"youtube":1,"news":1,"books":0,"products":0,"recipes":0,"functional":1},
{"domain":"google.com","tld":".com","country_name":"United States","language_a_code":"en","language_a_name":"English","web":1,"images":1,"youtube":1,"news":1,"books":1,"products":1,"recipes":1,"functional":1},
{"domain":"google.es","tld":".es","country_name":"Spain","language_a_code":"es","language_a_name":"Spanish","web":1,"images":1,"youtube":1,"news":1,"books":0,"products":0,"recipes":0,"functional":1},
{"domain":"google.ee","tld":".ee","country_name":"Estonia","language_a_code":"et","language_a_name":"Estonian","web":1,"images":0,"youtube":0,"news":0,"books":0,"products":0,"recipes":0,"functional":1},
{"domain":"google.fi","tld":".fi","country_name":"Finland","language_a_code":"fi","language_a_name":"Finnish","web":1,"images":1,"youtube":0,"news":0,"books":0,"products":0,"recipes":0,"functional":1},
{"domain":"google.fr","tld":".fr","country_name":"France","language_a_code":"fr","language_a_name":"French","web":1,"images":1,"youtube":1,"news":1,"books":0,"products":0,"recipes":0,"functional":1},
{"domain":"google.hr","tld":".hr","country_name":"Croatia","language_a_code":"hr","language_a_name":"Croatian","web":1,"images":1,"youtube":0,"news":0,"books":0,"products":0,"recipes":0,"functional":0},
{"domain":"google.hu","tld":".hu","country_name":"Hungary","language_a_code":"hu","language_a_name":"Hungarian","web":1,"images":1,"youtube":0,"news":0,"books":0,"products":0,"recipes":0,"functional":1},
{"domain":"google.co.id","tld":".id","country_name":"Indonesia","language_a_code":"id","language_a_name":"Indonesian","web":1,"images":1,"youtube":0,"news":0,"books":0,"products":0,"recipes":0,"functional":1},
{"domain":"google.is","tld":".is","country_name":"Iceland","language_a_code":"is","language_a_name":"Icelandic","web":1,"images":1,"youtube":0,"news":0,"books":0,"products":0,"recipes":0,"functional":1},
{"domain":"google.it","tld":".it","country_name":"Italy","language_a_code":"it","language_a_name":"Italian","web":1,"images":1,"youtube":1,"news":1,"books":0,"products":0,"recipes":0,"functional":1},
{"domain":"google.lt","tld":".lt","country_name":"Lithuania","language_a_code":"lt","language_a_name":"Lithuanian","web":1,"images":1,"youtube":0,"news":0,"books":0,"products":0,"recipes":0,"functional":0},
{"domain":"google.lv","tld":".lv","country_name":"Latvia","language_a_code":"lv","language_a_name":"Latvian","web":1,"images":0,"youtube":0,"news":0,"books":0,"products":0,"recipes":0,"functional":0},
{"domain":"google.mg","tld":".mg","country_name":"Madagascar","language_a_code":"mg","language_a_name":"Malagasy","web":1,"images":0,"youtube":0,"news":0,"books":0,"products":0,"recipes":0,"functional":0},
{"domain":"google.com.my","tld":".my","country_name":"Malaysia","language_a_code":"ms","language_a_name":"Malay","web":1,"images":0,"youtube":0,"news":0,"books":0,"products":0,"recipes":0,"functional":1},
{"domain":"google.nl","tld":".nl","country_name":"Netherlands","language_a_code":"nl","language_a_name":"Dutch","web":1,"images":1,"youtube":0,"news":0,"books":0,"products":0,"recipes":0,"functional":1},
{"domain":"google.no","tld":".no","country_name":"Norway","language_a_code":"no","language_a_name":"Norwegian","web":1,"images":1,"youtube":0,"news":0,"books":0,"products":0,"recipes":0,"functional":1},
{"domain":"google.pl","tld":".pl","country_name":"Poland","language_a_code":"pl","language_a_name":"Polish","web":1,"images":1,"youtube":1,"news":0,"books":0,"products":0,"recipes":0,"functional":0},
{"domain":"google.com.br","tld":".br","country_name":"Brazil","language_a_code":"pt-BR","language_a_name":"Portuguese (Brasil)","web":1,"images":1,"youtube":1,"news":0,"books":0,"products":0,"recipes":0,"functional":1},
{"domain":"google.pt","tld":".pt","country_name":"Portugal","language_a_code":"pt-PT","language_a_name":"Portuguese","web":1,"images":1,"youtube":0,"news":0,"books":0,"products":0,"recipes":0,"functional":1},
{"domain":"google.ro","tld":".ro","country_name":"Romania","language_a_code":"ro","language_a_name":"Romanian","web":1,"images":1,"youtube":0,"news":0,"books":0,"products":0,"recipes":0,"functional":1},
{"domain":"google.sk","tld":".sk","country_name":"Slovakia","language_a_code":"sk","language_a_name":"Slovak","web":1,"images":1,"youtube":0,"news":0,"books":0,"products":0,"recipes":0,"functional":0},
{"domain":"google.si","tld":".si","country_name":"Slovenia","language_a_code":"sl","language_a_name":"Slovenian","web":1,"images":0,"youtube":0,"news":0,"books":0,"products":0,"recipes":0,"functional":0},
{"domain":"google.rs","tld":".rs","country_name":"Serbia","language_a_code":"sr","language_a_name":"Serbian","web":1,"images":0,"youtube":0,"news":0,"books":0,"products":0,"recipes":0,"functional":1},
{"domain":"google.se","tld":".se","country_name":"Sweden","language_a_code":"sv","language_a_name":"Swedish","web":1,"images":1,"youtube":0,"news":0,"books":0,"products":0,"recipes":0,"functional":1},
{"domain":"google.co.ke","tld":".ke","country_name":"Kenya","language_a_code":"sw","language_a_name":"Swahili","web":1,"images":0,"youtube":0,"news":0,"books":0,"products":0,"recipes":0,"functional":1},
{"domain":"google.com.tr","tld":".tr","country_name":"Turkey","language_a_code":"tr","language_a_name":"Turkish","web":1,"images":1,"youtube":0,"news":0,"books":0,"products":0,"recipes":0,"functional":1},
{"domain":"google.com.vn","tld":".vn","country_name":"Vietnam","language_a_code":"vi","language_a_name":"Vietnamese","web":1,"images":1,"youtube":0,"news":0,"books":0,"products":0,"recipes":0,"functional":1}]